{"os_str":"iTunes","version":"4.7.1.30","safari_version":[],"build":"","key":"iTunes;4.7.1.30","embeddedOS_build":"","bridgeOS_build":"","build_train":"","released":"2005-01-11","rc":false,"beta":false,"rsr":false,"internal":false,"preinstalled":[],"notes":"","release_notes":"","security_notes":"","ipd":{},"appledb_web":{"web_image":{"id":"","align":"left"},"web_url":"https://appledb.dev/firmware/iTunes/4.7.1.30.html","api_url":"https://api.emiyl.com/firmware/iTunes/4.7.1.30.json","hide_from_latest_versions":false},"device_map":["iTunes (Windows, x86)"],"os_map":["Windows 2000","Windows XP"],"sources":[{"type":"exe","prerequisite_build":[],"device_map":["iTunes (Windows, x86)"],"os_map":["Windows 2000","Windows XP"],"windows_update_details":{"update_id":"","revision_id":""},"links":[{"url":"https://secure-appldnld.apple.com/iTunes4/WW/win/019-0312.20050111.MmVrT/iTunesSetup.exe","active":false}],"hashes":{"sha1":"e645f17113491b3af735d1d42865ee6deb6342ee"},"skip_update_links":false,"size":21848504}]}