{"os_str":"Safari","version":"13.0.4","build":"608C17","key":"Safari;608C17","released":"2019-12-10","rc":false,"beta":false,"rsr":false,"internal":false,"preinstalled":[],"appledb_web":{"web_image":{"id":"","align":"left"},"web_url":"https://appledb.dev/firmware/Safari/608C17.html","api_url":"https://api.emiyl.com/firmware/Safari/608C17.json","hide_from_latest_versions":false},"device_map":[{"name":"Safari (macOS)","key":"Safari (macOS)","released":["2003-01-07"]}],"device_group_map":[{"name":"Safari","key":"Safari","type":"Software","devices":["Safari (macOS)"],"hide_children":false,"subgroups":[]}],"sources":[{"type":"pkg","device_map":["Safari (macOS)"],"links":[{"url":"https://swcdn.apple.com/content/downloads/34/21/061-49175-A_H5579HY5LH/caq4203cu2klp24wpiw6n8fkjdqv1dxkl3/Safari13.0.4MojaveAuto.pkg","active":false}],"hashes":{},"size":68948292}]}