{"os_str":"Safari","version":"16.2 beta 5","build":"614C23","key":"Safari;614C23","released":"2022-12-07","rc":false,"beta":true,"rsr":false,"internal":false,"preinstalled":[],"appledb_web":{"web_image":{"id":"","align":"left"},"web_url":"https://appledb.dev/firmware/Safari/614C23.html","api_url":"https://api.emiyl.com/firmware/Safari/614C23.json","hide_from_latest_versions":false},"device_map":[{"name":"Safari (macOS)","key":"Safari (macOS)","released":["2003-01-07"]}],"device_group_map":[{"name":"Safari","key":"Safari","type":"Software","devices":["Safari (macOS)"],"hide_children":false,"subgroups":[]}],"sources":[{"type":"pkg","device_map":["Safari (macOS)"],"links":[{"url":"https://swcdn.apple.com/content/downloads/39/40/032-13014-A_SA5WOYJD3P/4we9qoscw5w45xt8hpm7iiidaycnqxqf1l/Safari16.2MontereyAutoSeed.pkg","active":false}],"hashes":{},"size":134052468}]}