{"os_str":"iOS","version":"16.0","safari_version":[],"build":"20A357","key":"iOS;20A357","embeddedOS_build":"","bridgeOS_build":"","build_train":"Sydney","released":"2022-09-16","rc":false,"beta":false,"rsr":false,"internal":false,"preinstalled":["iPhone14,7","iPhone14,8","iPhone15,2","iPhone15,3"],"notes":"","release_notes":"","security_notes":"","ipd":{},"appledb_web":{"web_image":{"id":"ios16","align":"left"},"web_url":"https://appledb.dev/firmware/iOS/20A357.html","api_url":"https://api.emiyl.com/firmware/iOS/20A357.json","hide_from_latest_versions":true},"device_map":["iPhone14,7","iPhone14,8","iPhone15,2","iPhone15,3"],"os_map":[],"sources":[]}