{"osStr":"Safari","version":"12.1 beta 5","safariVersion":[],"build":"607E25","key":"Safari;607E25","embeddedOSBuild":"","bridgeOSBuild":"","buildTrain":"","released":"2019-03-12","rc":false,"beta":true,"rsr":false,"internal":false,"preinstalled":[],"notes":"","releaseNotes":"","securityNotes":"","ipd":{},"appledb":{"webImage":{"id":"","align":"left"},"webUrl":"https://appledb.dev/firmware/Safari/607E25.html","apiUrl":"https://api.emiyl.com/firmware/Safari/607E25.json","hideFromLatestVersions":false},"deviceMap":["Safari (macOS)"],"osMap":["macOS 10.13"],"sources":[{"type":"pkg","prerequisiteBuild":[],"deviceMap":["Safari (macOS)"],"osMap":["macOS 10.13"],"windowsUpdateDetails":{"updateId":"","revisionId":""},"links":[{"url":"http://swcdn.apple.com/content/downloads/32/04/041-46315/pdflpsyu9lao3261rzrskt3q4gnrfzkgs4/Safari12.1HighSierraAutoSeed.pkg","active":false}],"hashes":{},"skipUpdateLinks":false,"size":81726831}]}