{"os_str":"Safari","version":"13.0.1 beta 2","safari_version":[],"build":"608A60","key":"Safari;608A60-beta","embeddedOS_build":"","bridgeOS_build":"","build_train":"","released":"2019-09-05","rc":false,"beta":true,"rsr":false,"internal":false,"preinstalled":[],"notes":"","release_notes":"","security_notes":"","ipd":{},"appledb_web":{"web_image":{"id":"","align":"left"},"web_url":"https://appledb.dev/firmware/Safari/608A60-beta.html","api_url":"https://api.emiyl.com/firmware/Safari/608A60-beta.json","hide_from_latest_versions":false},"device_map":["Safari (macOS)"],"os_map":["macOS 10.14"],"sources":[{"type":"pkg","prerequisite_build":[],"device_map":["Safari (macOS)"],"os_map":["macOS 10.14"],"windows_update_details":{"update_id":"","revision_id":""},"links":[{"url":"https://swcdn.apple.com/content/downloads/59/23/061-11626/kc2shswi62ks9crpumvz4ldlhtj1b383ky/Safari13.0.1MojaveAutoSeed.pkg","active":false}],"hashes":{},"skip_update_links":false,"size":68160910}]}