{"osStr":"Safari","version":"7.0.2","safariVersion":[],"build":"","key":"Safari;7.0.2","embeddedOSBuild":"","bridgeOSBuild":"","buildTrain":"","released":"2014-02-25","rc":false,"beta":false,"rsr":false,"internal":false,"preinstalled":[],"notes":"","releaseNotes":"","securityNotes":"https://support.apple.com/HT202921","ipd":{},"appledb":{"webImage":{"id":"","align":"left"},"webUrl":"https://appledb.dev/firmware/Safari/7.0.2.html","apiUrl":"https://api.emiyl.com/firmware/Safari/7.0.2.json","hideFromLatestVersions":false},"deviceMap":["Safari (macOS)"],"osMap":["OS X 10.9"],"sources":[]}