{"os_str":"Accessory Developer Assistant","version":"1.2","safari_version":[],"build":"1A260","key":"Accessory Developer Assistant;1A260","embeddedOS_build":"","bridgeOS_build":"","build_train":"","released":"2024-07-23","rc":false,"beta":false,"rsr":false,"internal":false,"preinstalled":[],"notes":"","release_notes":"","security_notes":"","ipd":{},"appledb_web":{"web_image":{"id":"","align":"left"},"web_url":"https://appledb.dev/firmware/Accessory-Developer-Assistant/1A260.html","api_url":"https://api.emiyl.com/firmware/Accessory%20Developer%20Assistant/1A260.json","hide_from_latest_versions":false},"device_map":["Accessory Developer Assistant"],"os_map":[],"sources":[]}