{"osStr":"Rosetta","version":"11.6.8 RC 4","safariVersion":[],"build":"20G728","key":"Rosetta;20G728","embeddedOSBuild":"","bridgeOSBuild":"","buildTrain":"","released":"2022-07-12","rc":true,"beta":false,"rsr":false,"internal":false,"preinstalled":[],"notes":"","releaseNotes":"","securityNotes":"","ipd":{},"appledb":{"webImage":{"id":"","align":"left"},"webUrl":"https://appledb.dev/firmware/Rosetta/20G728.html","apiUrl":"https://api.emiyl.com/firmware/Rosetta/20G728.json","hideFromLatestVersions":false},"deviceMap":["Rosetta"],"osMap":[],"sources":[{"type":"pkg","prerequisiteBuild":[],"deviceMap":["Rosetta"],"osMap":[],"windowsUpdateDetails":{"updateId":"","revisionId":""},"links":[{"url":"https://swcdn.apple.com/content/downloads/51/21/012-40386-A_M0LA659HA1/asg7utevqaqfyb1gb9a9edm3acn9lxkgso/RosettaUpdateAuto.pkg","active":true}],"hashes":{},"skipUpdateLinks":false,"size":200767}]}