{"osStr":"Rosetta","version":"12.7.2 RC 2","safariVersion":[],"build":"21G1965","key":"Rosetta;21G1965","embeddedOSBuild":"","bridgeOSBuild":"","buildTrain":"","released":"2023-11-10","rc":true,"beta":false,"rsr":false,"internal":false,"preinstalled":[],"notes":"","releaseNotes":"","securityNotes":"","ipd":{},"appledb":{"webImage":{"id":"","align":"left"},"webUrl":"https://appledb.dev/firmware/Rosetta/21G1965.html","apiUrl":"https://api.emiyl.com/firmware/Rosetta/21G1965.json","hideFromLatestVersions":false},"deviceMap":["Rosetta"],"osMap":[],"sources":[{"type":"pkg","prerequisiteBuild":[],"deviceMap":["Rosetta"],"osMap":[],"windowsUpdateDetails":{"updateId":"","revisionId":""},"links":[{"url":"https://swcdn.apple.com/content/downloads/37/24/052-02608-A_ZEITUN31KU/5g1tn78peoa1p9w5p8d1m5gyb3l1trz4mw/RosettaUpdateAuto.pkg","active":true}],"hashes":{},"skipUpdateLinks":false,"size":181927}]}