{"os_str":"Mac OS X","version":"10.4.7","build":"8K1106","key":"Mac OS X;8K1106","released":"2006-09-06","rc":false,"beta":false,"rsr":false,"internal":false,"preinstalled":["iMac5,1-17-inch","iMac5,1-20-inch","iMac5,2"],"appledb_web":{"web_image":{"id":"","align":"left"},"web_url":"https://appledb.dev/firmware/Mac-OS-X/8K1106.html","api_url":"https://api.emiyl.com/firmware/Mac%20OS%20X/8K1106.json","hide_from_latest_versions":false},"device_map":[{"name":"iMac (17-inch, Late 2006, Dedicated Graphics)","key":"iMac5,1-17-inch","released":["2006-09-06"]},{"name":"iMac (20-inch, Late 2006)","key":"iMac5,1-20-inch","released":["2006-09-06"]},{"name":"iMac (17-inch, Late 2006, Integrated Graphics)","key":"iMac5,2","released":["2006-09-06"]}],"device_group_map":[{"name":"iMac (17-inch, Late 2006)","key":"iMac (17-inch, Late 2006)","type":"iMac","devices":["iMac5,1-17-inch","iMac5,2"],"hide_children":false,"subgroups":[]},{"name":"iMac (20-inch, Late 2006)","key":"iMac5,1-20-inch","type":"","devices":["iMac5,1-20-inch"],"hide_children":false,"subgroups":[]}],"sources":[]}