{"os_str":"Mac OS X","version":"10.5","build":"9A3115A","key":"Mac OS X;9A3115A","released":"","rc":false,"beta":false,"rsr":false,"internal":false,"preinstalled":[],"appledb_web":{"web_image":{"id":"","align":"left"},"web_url":"https://appledb.dev/firmware/Mac-OS-X/9A3115A.html","api_url":"https://api.emiyl.com/firmware/Mac%20OS%20X/9A3115A.json","hide_from_latest_versions":false},"device_map":[{"name":"MacBook (13-inch, Late 2007)","key":"MacBook3,1","released":["2007-11-01"]}],"device_group_map":[{"name":"MacBook (13-inch, Late 2007)","key":"MacBook3,1","type":"","devices":["MacBook3,1"],"hide_children":false,"subgroups":[]}],"sources":[]}