{"os_str":"Pixo","version":"1.1.3","safari_version":[],"build":"135495680","key":"Pixo;135495680","embeddedOS_build":"","bridgeOS_build":"","build_train":"","released":"2007-04-24","rc":false,"beta":false,"rsr":false,"internal":false,"preinstalled":[],"notes":"","release_notes":"","security_notes":"","ipd":{},"appledb_web":{"web_image":{"id":"","align":"left"},"web_url":"https://appledb.dev/firmware/Pixo/135495680.html","api_url":"https://api.emiyl.com/firmware/Pixo/135495680.json","hide_from_latest_versions":false},"device_map":["iPod nano (2nd generation rev A)","iPod nano (2nd generation)"],"os_map":[],"sources":[{"type":"ipsw","prerequisite_build":[],"device_map":["iPod nano (2nd generation rev A)"],"os_map":[],"windows_update_details":{"update_id":"","revision_id":""},"links":[{"url":"https://secure-appldnld.apple.com/iPod/SBML/osx/bundles/061-3326.20070507.0Pm87/iPod_29.1.1.3.ipsw","active":true}],"hashes":{"md5":"8acade1b8d3c4cc24afbd7be8ad9f727"},"skip_update_links":false,"size":21866613},{"type":"ipsw","prerequisite_build":[],"device_map":["iPod nano (2nd generation)"],"os_map":[],"windows_update_details":{"update_id":"","revision_id":""},"links":[{"url":"https://secure-appldnld.apple.com/iPod/SBML/osx/bundles/061-3325.20070507.KnB7v/iPod_19.1.1.3.ipsw","active":true}],"hashes":{"md5":"769ea429e823376d3098919f898717e2"},"skip_update_links":false,"size":21866626}]}