{"os_str":"Durian Firmware","version":"1.0.225","build":"","key":"Durian Firmware;1.0.225","released":"2021-04-30","rc":false,"beta":false,"rsr":false,"internal":false,"preinstalled":["AirTag1,1"],"appledb_web":{"web_image":{"id":"","align":"left"},"web_url":"https://appledb.dev/firmware/Durian-Firmware/1.0.225.html","api_url":"https://api.emiyl.com/firmware/Durian%20Firmware/1.0.225.json","hide_from_latest_versions":false},"device_map":[{"name":"AirTag","key":"AirTag1,1","released":["2021-04-30"]}],"device_group_map":[{"name":"AirTag","key":"AirTag1,1","type":"","devices":["AirTag1,1"],"hide_children":false,"subgroups":[]}],"sources":[]}