{"os_str":"tvOS","version":"13.3 Simulator","safari_version":[],"build":"17K446","key":"tvOS;17K446-sim","embeddedOS_build":"","bridgeOS_build":"","build_train":"","released":"2019-12-10","rc":false,"beta":false,"rsr":false,"internal":false,"preinstalled":[],"notes":"","release_notes":"","security_notes":"","ipd":{},"appledb_web":{"web_image":{"id":"","align":"left"},"web_url":"https://appledb.dev/firmware/tvOS/17K446-sim.html","api_url":"https://api.emiyl.com/firmware/tvOS/17K446-sim.json","hide_from_latest_versions":false},"device_map":["tvOS Simulator"],"os_map":[],"sources":[{"type":"dmg","prerequisite_build":[],"device_map":["tvOS Simulator"],"os_map":[],"windows_update_details":{"update_id":"","revision_id":""},"links":[{"url":"https://devimages-cdn.apple.com/downloads/xcode/simulators/com.apple.pkg.AppleTVSimulatorSDK13_3-13.3.1.1580170331.dmg","active":true}],"hashes":{"md5":"93d83cfec44a5d1eb65894e5e8cf13a1"},"skip_update_links":false,"size":1542265613}]}