{"os_str":"macOS","version":"10.13.3 (Supplemental Update)","build":"17D2103","key":"macOS;17D2103","released":"2018-03-01","rc":false,"beta":false,"rsr":false,"internal":false,"preinstalled":[],"appledb_web":{"web_image":{"id":"High Sierra","align":"left"},"web_url":"https://appledb.dev/firmware/macOS/17D2103.html","api_url":"https://api.emiyl.com/firmware/macOS/17D2103.json","hide_from_latest_versions":false},"device_map":[{"name":"iMac Pro (Retina 5K, 27-inch, Late 2017)","key":"iMacPro1,1","released":["2017-12-14"]}],"device_group_map":[{"name":"iMac Pro (Retina 5K, 27-inch, Late 2017)","key":"iMac Pro (Retina 5K, 27-inch, Late 2017)","type":"iMac","devices":["iMacPro1,1"],"hide_children":false,"subgroups":[]}],"sources":[{"type":"update","device_map":["iMacPro1,1"],"links":[{"url":"https://updates.cdn-apple.com/2019/cert/041-90810-20191011-68435a16-e48f-4d45-9287-2bee950f77a6/macOSUpd10.13.3iMacProSupplemental.dmg","active":true}],"hashes":{"md5":"1e63d6a98d00390973b3a2f250001eb6","sha1":"50bbe9c815fd08b1adbf5628e43252ef7f8eb875"},"size":589990151}]}