{"os_str":"Rosetta","version":"11.6.1 RC","build":"20G211","key":"Rosetta;20G211","released":"2021-09-29","rc":true,"beta":false,"rsr":false,"internal":false,"preinstalled":[],"appledb_web":{"web_image":{"id":"","align":"left"},"web_url":"https://appledb.dev/firmware/Rosetta/20G211.html","api_url":"https://api.emiyl.com/firmware/Rosetta/20G211.json","hide_from_latest_versions":false},"device_map":[{"name":"Rosetta","key":"Rosetta","released":["2020-09-17"]}],"device_group_map":[{"name":"Rosetta","key":"Rosetta","type":"","devices":["Rosetta"],"hide_children":false,"subgroups":[]}],"sources":[{"type":"pkg","device_map":["Rosetta"],"links":[{"url":"https://swcdn.apple.com/content/downloads/36/22/002-09108-A_HVHO87F3QC/df9nasif58pe7ewagq5rfttwza8q7ld3pb/RosettaUpdateAuto.pkg","active":true}],"hashes":{"sha1":"be64fa2824e278f9816003d7ff6fc94e76dc789d"},"size":200921}]}