{"os_str":"Wireless Remote Firmware","version":"0x0254","safari_version":[],"build":"","key":"Wireless Remote Firmware;0x0254","embeddedOS_build":"","bridgeOS_build":"","build_train":"","released":"2018-08-28","rc":false,"beta":false,"rsr":false,"internal":false,"preinstalled":[],"notes":"","release_notes":"","security_notes":"","ipd":{},"appledb_web":{"web_image":{"id":"","align":"left"},"web_url":"https://appledb.dev/firmware/Wireless-Remote-Firmware/0x0254.html","api_url":"https://api.emiyl.com/firmware/Wireless%20Remote%20Firmware/0x0254.json","hide_from_latest_versions":false},"device_map":["ATVRemote1,1"],"os_map":[],"sources":[{"type":"ota","prerequisite_build":[],"device_map":["ATVRemote1,1"],"os_map":[],"windows_update_details":{"update_id":"","revision_id":""},"links":[{"url":"https://updates.cdn-apple.com/2018/ios/091-84414-20180828-766FD216-A70E-11E8-9880-9845A9B60D77/com_apple_MobileAsset_MobileAccessoryUpdate_WirelessRemoteFirmware/6099063c6e8a2825818df267457513764f52b4ef.zip","active":true}],"hashes":{"md5":"c5e833201a2111f9ad399a530732a1fd"},"skip_update_links":false,"size":238593}]}