{"os_str":"Mac OS X","version":"10.3.5","safari_version":[],"build":"7P35","key":"Mac OS X;7P35","embeddedOS_build":"","bridgeOS_build":"","build_train":"","released":"2004-08-31","rc":false,"beta":false,"rsr":false,"internal":false,"preinstalled":["PowerMac8,1-17-inch","PowerMac8,1-20-inch"],"notes":"","release_notes":"","security_notes":"","ipd":{},"appledb_web":{"web_image":{"id":"","align":"left"},"web_url":"https://appledb.dev/firmware/Mac-OS-X/7P35.html","api_url":"https://api.emiyl.com/firmware/Mac%20OS%20X/7P35.json","hide_from_latest_versions":false},"device_map":["PowerMac8,1-17-inch","PowerMac8,1-20-inch"],"os_map":[],"sources":[]}