{"os_str":"bridgeOS","version":"3.1","safari_version":[],"build":"16P1578","key":"bridgeOS;16P1578","embeddedOS_build":"","bridgeOS_build":"","build_train":"bridgeOSLibertyBHW","released":"2018-10-30","rc":false,"beta":false,"rsr":false,"internal":false,"preinstalled":["iBridge2,8"],"notes":"","release_notes":"","security_notes":"","ipd":{},"appledb_web":{"web_image":{"id":"","align":"left"},"web_url":"https://appledb.dev/firmware/bridgeOS/16P1578.html","api_url":"https://api.emiyl.com/firmware/bridgeOS/16P1578.json","hide_from_latest_versions":false},"device_map":["iBridge2,8"],"os_map":[],"sources":[]}