[{"name":"iPod nano (2nd generation)","key":"iPod nano (2nd generation)","type":"iPod nano","devices":["iPod nano (2nd generation)","iPod nano (2nd generation rev A)"],"hide_children":false,"subgroups":[]},{"name":"iPod nano (7th generation)","key":"iPod nano (7th generation)","type":"iPod nano","devices":["iPod nano (7th generation)","iPod nano (7th generation Mid 2015)"],"hide_children":false,"subgroups":[]},{"name":"iPod nano","key":"iPod nano","type":"iPod nano","devices":["iPod nano","iPod nano-revision"],"hide_children":false,"subgroups":[]},{"name":"iPod mini","key":"iPod mini","type":"iPod mini","devices":["iPod mini from HP Music Player","iPod mini","iPod mini-revision"],"hide_children":false,"subgroups":[]},{"name":"Mac Studio (2023)","key":"Mac Studio (2023)","type":"Mac Studio","devices":["Mac14,13","Mac14,14"],"hide_children":false,"subgroups":[]},{"name":"Mac Studio (2022)","key":"Mac Studio (2022)","type":"Mac Studio","devices":["Mac13,1","Mac13,2"],"hide_children":false,"subgroups":[]},{"name":"iPhone 12 Pro","key":"iPhone 12 Pro series","type":"iPhone","devices":["iPhone13,3","iPhone13,4"],"hide_children":false,"subgroups":[{"name":"iPhone 12 Pro","key":"iPhone 12 Pro","type":"iPhone","devices":["iPhone13,3"],"hide_children":false,"subgroups":[]},{"name":"iPhone 12 Pro Max","key":"iPhone 12 Pro Max","type":"iPhone","devices":["iPhone13,4"],"hide_children":false,"subgroups":[]}]},{"name":"iPhone 5c","key":"iPhone 5c","type":"iPhone","devices":["iPhone5,3","iPhone5,4"],"hide_children":false,"subgroups":[]},{"name":"iPhone 12","key":"iPhone 12 series","type":"iPhone","devices":["iPhone13,1","iPhone13,2"],"hide_children":false,"subgroups":[{"name":"iPhone 12","key":"iPhone 12","type":"iPhone","devices":["iPhone13,2"],"hide_children":false,"subgroups":[]},{"name":"iPhone 12 mini","key":"iPhone 12 mini","type":"iPhone","devices":["iPhone13,1"],"hide_children":false,"subgroups":[]}]},{"name":"iPhone 6","key":"iPhone 6 series","type":"iPhone","devices":["iPhone7,1","iPhone7,2"],"hide_children":false,"subgroups":[{"name":"iPhone 6","key":"iPhone 6","type":"iPhone","devices":["iPhone7,2"],"hide_children":false,"subgroups":[]},{"name":"iPhone 6 Plus","key":"iPhone 6 Plus","type":"iPhone","devices":["iPhone7,1"],"hide_children":false,"subgroups":[]}]},{"name":"iPhone 6s","key":"iPhone 6s series","type":"iPhone","devices":["iPhone8,1","iPhone8,2"],"hide_children":false,"subgroups":[{"name":"iPhone 6s","key":"iPhone 6s","type":"iPhone","devices":["iPhone8,1"],"hide_children":false,"subgroups":[]},{"name":"iPhone 6s Plus","key":"iPhone 6s Plus","type":"iPhone","devices":["iPhone8,2"],"hide_children":false,"subgroups":[]}]},{"name":"iPhone 13 Pro","key":"iPhone 13 Pro series","type":"iPhone","devices":["iPhone14,2","iPhone14,3"],"hide_children":false,"subgroups":[{"name":"iPhone 13 Pro","key":"iPhone 13 Pro","type":"iPhone","devices":["iPhone14,2"],"hide_children":false,"subgroups":[]},{"name":"iPhone 13 Pro Max","key":"iPhone 13 Pro Max","type":"iPhone","devices":["iPhone14,3"],"hide_children":false,"subgroups":[]}]},{"name":"iPhone X","key":"iPhone X","type":"iPhone","devices":["iPhone10,3","iPhone10,6"],"hide_children":false,"subgroups":[]},{"name":"iPhone 2G","key":"iPhone 2G","type":"iPhone","devices":["iPhone1,1"],"hide_children":false,"subgroups":[]},{"name":"iPhone 5","key":"iPhone 5","type":"iPhone","devices":["iPhone5,1","iPhone5,2"],"hide_children":false,"subgroups":[]},{"name":"iPhone 16 Pro","key":"iPhone 16 Pro series","type":"iPhone","devices":["iPhone17,1","iPhone17,2"],"hide_children":false,"subgroups":[{"name":"iPhone 16 Pro","key":"iPhone 16 Pro","type":"iPhone","devices":["iPhone17,1"],"hide_children":false,"subgroups":[]},{"name":"iPhone 16 Pro Max","key":"iPhone 16 Pro Max","type":"iPhone","devices":["iPhone17,2"],"hide_children":false,"subgroups":[]}]},{"name":"iPhone 15","key":"iPhone 15 series","type":"iPhone","devices":["iPhone15,4","iPhone15,5"],"hide_children":false,"subgroups":[{"name":"iPhone 15","key":"iPhone 15","type":"iPhone","devices":["iPhone15,4"],"hide_children":false,"subgroups":[]},{"name":"iPhone 15 Plus","key":"iPhone 15 Plus","type":"iPhone","devices":["iPhone15,5"],"hide_children":false,"subgroups":[]}]},{"name":"iPhone 14","key":"iPhone 14 series","type":"iPhone","devices":["iPhone14,7","iPhone14,8"],"hide_children":false,"subgroups":[{"name":"iPhone 14","key":"iPhone 14","type":"iPhone","devices":["iPhone14,7"],"hide_children":false,"subgroups":[]},{"name":"iPhone 14 Plus","key":"iPhone 14 Plus","type":"iPhone","devices":["iPhone14,8"],"hide_children":false,"subgroups":[]}]},{"name":"iPhone 5s","key":"iPhone 5s","type":"iPhone","devices":["iPhone6,1","iPhone6,2"],"hide_children":false,"subgroups":[]},{"name":"iPhone 14 Pro","key":"iPhone 14 Pro series","type":"iPhone","devices":["iPhone15,2","iPhone15,3"],"hide_children":false,"subgroups":[{"name":"iPhone 14 Pro","key":"iPhone 14 Pro","type":"iPhone","devices":["iPhone15,2"],"hide_children":false,"subgroups":[]},{"name":"iPhone 14 Pro Max","key":"iPhone 14 Pro Max","type":"iPhone","devices":["iPhone15,3"],"hide_children":false,"subgroups":[]}]},{"name":"iPhone 16","key":"iPhone 16 series","type":"iPhone","devices":["iPhone17,3","iPhone17,4"],"hide_children":false,"subgroups":[{"name":"iPhone 16","key":"iPhone 16","type":"iPhone","devices":["iPhone17,3"],"hide_children":false,"subgroups":[]},{"name":"iPhone 16 Plus","key":"iPhone 16 Plus","type":"iPhone","devices":["iPhone17,4"],"hide_children":false,"subgroups":[]}]},{"name":"iPhone 8","key":"iPhone 8 series","type":"iPhone","devices":["iPhone10,1","iPhone10,2","iPhone10,4","iPhone10,5"],"hide_children":false,"subgroups":[{"name":"iPhone 8","key":"iPhone 8","type":"iPhone","devices":["iPhone10,1","iPhone10,4"],"hide_children":false,"subgroups":[]},{"name":"iPhone 8 Plus","key":"iPhone 8 Plus","type":"iPhone","devices":["iPhone10,2","iPhone10,5"],"hide_children":false,"subgroups":[]}]},{"name":"iPhone 13","key":"iPhone 13 series","type":"iPhone","devices":["iPhone14,4","iPhone14,5"],"hide_children":false,"subgroups":[{"name":"iPhone 13","key":"iPhone 13","type":"iPhone","devices":["iPhone14,5"],"hide_children":false,"subgroups":[]},{"name":"iPhone 13 mini","key":"iPhone 13 mini","type":"iPhone","devices":["iPhone14,4"],"hide_children":false,"subgroups":[]}]},{"name":"iPhone XS","key":"iPhone XS series","type":"iPhone","devices":["iPhone11,2","iPhone11,4","iPhone11,6"],"hide_children":false,"subgroups":[{"name":"iPhone XS","key":"iPhone XS","type":"iPhone","devices":["iPhone11,2"],"hide_children":false,"subgroups":[]},{"name":"iPhone XS Max","key":"iPhone XS Max","type":"iPhone","devices":["iPhone11,4","iPhone11,6"],"hide_children":false,"subgroups":[]}]},{"name":"iPhone 11 Pro","key":"iPhone 11 Pro series","type":"iPhone","devices":["iPhone12,3","iPhone12,5"],"hide_children":false,"subgroups":[{"name":"iPhone 11 Pro","key":"iPhone 11 Pro","type":"iPhone","devices":["iPhone12,3"],"hide_children":false,"subgroups":[]},{"name":"iPhone 11 Pro Max","key":"iPhone 11 Pro Max","type":"iPhone","devices":["iPhone12,5"],"hide_children":false,"subgroups":[]}]},{"name":"iPhone 4","key":"iPhone 4","type":"iPhone","devices":["iPhone3,1","iPhone3,2","iPhone3,3"],"hide_children":false,"subgroups":[]},{"name":"iPhone 15 Pro","key":"iPhone 15 Pro series","type":"iPhone","devices":["iPhone16,1","iPhone16,2"],"hide_children":false,"subgroups":[{"name":"iPhone 15 Pro","key":"iPhone 15 Pro","type":"iPhone","devices":["iPhone16,1"],"hide_children":false,"subgroups":[]},{"name":"iPhone 15 Pro Max","key":"iPhone 15 Pro Max","type":"iPhone","devices":["iPhone16,2"],"hide_children":false,"subgroups":[]}]},{"name":"iPhone 7","key":"iPhone 7 series","type":"iPhone","devices":["iPhone9,1","iPhone9,2","iPhone9,3","iPhone9,4"],"hide_children":false,"subgroups":[{"name":"iPhone 7","key":"iPhone 7","type":"iPhone","devices":["iPhone9,1","iPhone9,3"],"hide_children":false,"subgroups":[]},{"name":"iPhone 7 Plus","key":"iPhone 7 Plus","type":"iPhone","devices":["iPhone9,2","iPhone9,4"],"hide_children":false,"subgroups":[]}]},{"name":"Mac mini (Late 2012)","key":"Mac mini (Late 2012)","type":"Mac mini","devices":["Macmini6,1","Macmini6,2"],"hide_children":false,"subgroups":[]},{"name":"Mac mini (Mid 2011)","key":"Mac mini (Mid 2011)","type":"Mac mini","devices":["Macmini5,1","Macmini5,2","Macmini5,3"],"hide_children":false,"subgroups":[]},{"name":"Mac mini (2024)","key":"Mac mini (2024)","type":"Mac mini","devices":["Mac16,10","Mac16,11"],"hide_children":false,"subgroups":[]},{"name":"Mac mini (2023)","key":"Mac mini (2023)","type":"Mac mini","devices":["Mac14,3","Mac14,12"],"hide_children":false,"subgroups":[]},{"name":"AirPods 4","key":"AirPods 4","type":"AirPods","devices":["AirPods3,2-left","AirPods3,2-right","AirPods3,2-case"],"hide_children":false,"subgroups":[]},{"name":"AirPods Pro (2nd generation, USB-C)","key":"AirPods Pro (2nd generation, USB-C)","type":"AirPods","devices":["Device1,8228-left","Device1,8228-right","Device1,8228-case"],"hide_children":false,"subgroups":[]},{"name":"AirPods Pro (2nd generation)","key":"AirPods Pro (2nd generation)","type":"AirPods","devices":["AirPods3,1-left","AirPods3,1-right","MagSafe Charging Case for AirPods Pro (2nd generation)","Device1,8228-case"],"hide_children":false,"subgroups":[]},{"name":"AirPods Pro (1st generation)","key":"AirPods Pro (1st generation)","type":"AirPods","devices":["AirPods2,2-left","AirPods2,2-right","AirPods Pro Charging Case","MagSafe Charging Case for AirPods Pro"],"hide_children":false,"subgroups":[]},{"name":"AirPods 4 with Active Noise Cancellation","key":"AirPods 4 with Active Noise Cancellation","type":"AirPods","devices":["AirPods3,3-left","AirPods3,3-right","AirPods3,3-case"],"hide_children":false,"subgroups":[]},{"name":"AirPods (2nd generation)","key":"AirPods (2nd generation)","type":"AirPods","devices":["AirPods2,1-left","AirPods2,1-right","Wireless Charging Case","Lightning Charging Case"],"hide_children":false,"subgroups":[]},{"name":"AirPods (3rd generation)","key":"AirPods (3rd generation)","type":"AirPods","devices":["Audio2,1-left","Audio2,1-right","MagSafe Charging Case for AirPods (3rd generation)","Lightning Charging Case for AirPods (3rd generation)"],"hide_children":false,"subgroups":[]},{"name":"AirPods (1st generation)","key":"AirPods (1st generation)","type":"AirPods","devices":["AirPods1,1-left","AirPods1,1-right","Lightning Charging Case","Wireless Charging Case"],"hide_children":false,"subgroups":[]},{"name":"iPod (Dock Connector)","key":"iPod (Dock Connector)","type":"iPod","devices":["iPod (Dock Connector)","iPod (Dock Connector)-revisionA","iPod (Dock Connector)-revisionB"],"hide_children":false,"subgroups":[]},{"name":"iPod with video","key":"iPod with video","type":"iPod","devices":["iPod with video","iPod with video (Late 2006)","iPod with video-u2","iPod with video-lateu2","iPod with video-harrypotter"],"hide_children":false,"subgroups":[]},{"name":"iPod (Click Wheel)","key":"iPod (Click Wheel)","type":"iPod","devices":["iPod (Click Wheel)-u2","iPod (Click Wheel)","iPod from HP Color Music Player","iPod from HP Music Player","iPod photo-revision","iPod photo","iPod with color display-u2","iPod with color display-harrypotter","iPod with color display"],"hide_children":false,"subgroups":[]},{"name":"iPod (Scroll Wheel)","key":"iPod (Scroll Wheel)","type":"iPod","devices":["iPod (Scroll Wheel)","iPod (Scroll Wheel)-revision","iPod (Scroll Wheel)-beck","iPod (Scroll Wheel)-tonyhawk","iPod (Scroll Wheel)-madonna","iPod (Scroll Wheel)-nodoubt"],"hide_children":false,"subgroups":[]},{"name":"iPod (Touch Wheel)","key":"iPod (Touch Wheel)","type":"iPod","devices":["iPod (Touch Wheel)","iPod (Touch Wheel)-beck","iPod (Touch Wheel)-tonyhawk","iPod (Touch Wheel)-madonna","iPod (Touch Wheel)-nodoubt"],"hide_children":false,"subgroups":[]},{"name":"iPod classic","key":"iPod classic","type":"iPod","devices":["iPod classic","iPod classic (Late 2008)","iPod classic (Late 2009)","iPod classic (Late 2012)"],"hide_children":false,"subgroups":[]},{"name":"iPad mini (A17 Pro)","key":"iPad mini (A17 Pro)","type":"iPad mini","devices":["iPad16,1","iPad16,2"],"hide_children":false,"subgroups":[]},{"name":"iPad Pro 12.9-inch (6th generation)","key":"iPad Pro 12.9-inch (6th generation)","type":"iPad Pro","devices":["iPad14,5","iPad14,6"],"hide_children":false,"subgroups":[]},{"name":"iPad mini 3","key":"iPad mini 3","type":"iPad mini","devices":["iPad4,7","iPad4,8","iPad4,9"],"hide_children":false,"subgroups":[]},{"name":"iPad (4th generation)","key":"iPad (4th generation)","type":"iPad","devices":["iPad3,4","iPad3,5","iPad3,6"],"hide_children":false,"subgroups":[]},{"name":"iPad Air (4th generation)","key":"iPad Air (4th generation)","type":"iPad Air","devices":["iPad13,1","iPad13,2"],"hide_children":false,"subgroups":[]},{"name":"iPad Pro 12.9-inch (4th generation)","key":"iPad Pro 12.9-inch (4th generation)","type":"iPad Pro","devices":["iPad8,11","iPad8,12"],"hide_children":false,"subgroups":[]},{"name":"iPad (3rd generation)","key":"iPad (3rd generation)","type":"iPad","devices":["iPad3,1","iPad3,2","iPad3,3"],"hide_children":false,"subgroups":[]},{"name":"iPad Air","key":"iPad Air","type":"iPad Air","devices":["iPad4,1","iPad4,2","iPad4,3"],"hide_children":false,"subgroups":[]},{"name":"iPad Pro (9.7-inch)","key":"iPad Pro (9.7-inch)","type":"iPad Pro","devices":["iPad6,3","iPad6,4"],"hide_children":false,"subgroups":[]},{"name":"iPad Air (5th generation)","key":"iPad Air (5th generation)","type":"iPad Air","devices":["iPad13,16","iPad13,17"],"hide_children":false,"subgroups":[]},{"name":"iPad mini (5th generation)","key":"iPad mini (5th generation)","type":"iPad mini","devices":["iPad11,1","iPad11,2"],"hide_children":false,"subgroups":[]},{"name":"iPad Pro 13-inch (M4)","key":"iPad Pro 13-inch (M4)","type":"iPad Pro","devices":["iPad16,5","iPad16,6"],"hide_children":false,"subgroups":[]},{"name":"iPad Air 2","key":"iPad Air 2","type":"iPad Air","devices":["iPad5,3","iPad5,4"],"hide_children":false,"subgroups":[]},{"name":"iPad Pro 12.9-inch (3rd generation)","key":"iPad Pro 12.9-inch (3rd generation)","type":"iPad Pro","devices":["iPad8,5","iPad8,6","iPad8,7","iPad8,8"],"hide_children":false,"subgroups":[]},{"name":"iPad Air (3rd generation)","key":"iPad Air (3rd generation)","type":"iPad Air","devices":["iPad11,3","iPad11,4"],"hide_children":false,"subgroups":[]},{"name":"iPad Pro (10.5-inch)","key":"iPad Pro (10.5-inch)","type":"iPad Pro","devices":["iPad7,3","iPad7,4"],"hide_children":false,"subgroups":[]},{"name":"iPad (5th generation)","key":"iPad (5th generation)","type":"iPad","devices":["iPad6,11","iPad6,12"],"hide_children":false,"subgroups":[]},{"name":"iPad Pro 11-inch (3rd generation)","key":"iPad Pro 11-inch (3rd generation)","type":"iPad Pro","devices":["iPad13,4","iPad13,5","iPad13,6","iPad13,7"],"hide_children":false,"subgroups":[]},{"name":"iPad 2","key":"iPad 2","type":"iPad","devices":["iPad2,1","iPad2,2","iPad2,3","iPad2,4"],"hide_children":false,"subgroups":[]},{"name":"iPad Air 13-inch (M2)","key":"iPad Air 13-inch (M2)","type":"iPad Air","devices":["iPad14,10","iPad14,11"],"hide_children":false,"subgroups":[]},{"name":"iPad mini 4","key":"iPad mini 4","type":"iPad mini","devices":["iPad5,1","iPad5,2"],"hide_children":false,"subgroups":[]},{"name":"iPad (6th generation)","key":"iPad (6th generation)","type":"iPad","devices":["iPad7,5","iPad7,6"],"hide_children":false,"subgroups":[]},{"name":"iPad (10th generation)","key":"iPad (10th generation)","type":"iPad","devices":["iPad13,18","iPad13,19"],"hide_children":false,"subgroups":[]},{"name":"iPad Pro 11-inch (M4)","key":"iPad Pro 11-inch (M4)","type":"iPad Pro","devices":["iPad16,3","iPad16,4"],"hide_children":false,"subgroups":[]},{"name":"iPad Pro 12.9-inch (5th generation)","key":"iPad Pro 12.9-inch (5th generation)","type":"iPad Pro","devices":["iPad13,8","iPad13,9","iPad13,10","iPad13,11"],"hide_children":false,"subgroups":[]},{"name":"iPad Air 11-inch (M2)","key":"iPad Air 11-inch (M2)","type":"iPad Air","devices":["iPad14,8","iPad14,9"],"hide_children":false,"subgroups":[]},{"name":"iPad Pro (12.9-inch) (2nd generation)","key":"iPad Pro (12.9-inch) (2nd generation)","type":"iPad Pro","devices":["iPad7,1","iPad7,2"],"hide_children":false,"subgroups":[]},{"name":"iPad (7th generation)","key":"iPad (7th generation)","type":"iPad","devices":["iPad7,11","iPad7,12"],"hide_children":false,"subgroups":[]},{"name":"iPad Pro (12.9-inch) (1st generation)","key":"iPad Pro (12.9-inch) (1st generation)","type":"iPad Pro","devices":["iPad6,7","iPad6,8"],"hide_children":false,"subgroups":[]},{"name":"iPad mini 2","key":"iPad mini 2","type":"iPad mini","devices":["iPad4,4","iPad4,5","iPad4,6"],"hide_children":false,"subgroups":[]},{"name":"iPad (9th generation)","key":"iPad (9th generation)","type":"iPad","devices":["iPad12,1","iPad12,2"],"hide_children":false,"subgroups":[]},{"name":"iPad Pro 11-inch (1st generation)","key":"iPad Pro 11-inch (1st generation)","type":"iPad Pro","devices":["iPad8,1","iPad8,2","iPad8,3","iPad8,4"],"hide_children":false,"subgroups":[]},{"name":"iPad mini (6th generation)","key":"iPad mini (6th generation)","type":"iPad mini","devices":["iPad14,1","iPad14,2"],"hide_children":false,"subgroups":[]},{"name":"iPad Pro 11-inch (4th generation)","key":"iPad Pro 11-inch (4th generation)","type":"iPad Pro","devices":["iPad14,3","iPad14,4"],"hide_children":false,"subgroups":[]},{"name":"iPad (8th generation)","key":"iPad (8th generation)","type":"iPad","devices":["iPad11,6","iPad11,7"],"hide_children":false,"subgroups":[]},{"name":"iPad Pro 11-inch (2nd generation)","key":"iPad Pro 11-inch (2nd generation)","type":"iPad Pro","devices":["iPad8,9","iPad8,10"],"hide_children":false,"subgroups":[]},{"name":"iPad mini","key":"iPad mini","type":"iPad mini","devices":["iPad2,5","iPad2,6","iPad2,7"],"hide_children":false,"subgroups":[]},{"name":"MacBook Pro (14-inch, Nov 2023)","key":"MacBook Pro (14-inch, Nov 2023)","type":"MacBook Pro","devices":["Mac15,3","Mac15,6","Mac15,8","Mac15,10"],"hide_children":false,"subgroups":[]},{"name":"MacBook Pro (13-inch, 2017)","key":"MacBook Pro (13-inch, 2017)","type":"MacBook Pro","devices":["MacBookPro14,1","MacBookPro14,2"],"hide_children":false,"subgroups":[]},{"name":"MacBook Pro (16-inch, 2019)","key":"MacBook Pro (16-inch, 2019)","type":"MacBook Pro","devices":["MacBookPro16,1","MacBookPro16,4"],"hide_children":false,"subgroups":[]},{"name":"MacBook Pro (14-inch, 2023)","key":"MacBook Pro (14-inch, 2023)","type":"MacBook Pro","devices":["Mac14,9","Mac14,5"],"hide_children":false,"subgroups":[]},{"name":"MacBook Pro (13-inch, 2016)","key":"MacBook Pro (13-inch, 2016)","type":"MacBook Pro","devices":["MacBookPro13,1","MacBookPro13,2"],"hide_children":false,"subgroups":[]},{"name":"MacBook Pro (16-inch, Nov 2024)","key":"MacBook Pro (16-inch, Nov 2024)","type":"MacBook Pro","devices":["Mac16,5","Mac16,7"],"hide_children":false,"subgroups":[]},{"name":"MacBook Pro (Retina, 15-inch, Mid 2015)","key":"MacBook Pro (Retina, 15-inch, Mid 2015)","type":"MacBook Pro","devices":["MacBookPro11,4","MacBookPro11,5"],"hide_children":false,"subgroups":[]},{"name":"MacBook Pro (13-inch, 2020)","key":"MacBook Pro (13-inch, 2020)","type":"MacBook Pro","devices":["MacBookPro16,2","MacBookPro16,3"],"hide_children":false,"subgroups":[]},{"name":"MacBook Pro (16-inch, 2023)","key":"MacBook Pro (16-inch, 2023)","type":"MacBook Pro","devices":["Mac14,10","Mac14,6"],"hide_children":false,"subgroups":[]},{"name":"MacBook Pro (16-inch, Nov 2023)","key":"MacBook Pro (16-inch, Nov 2023)","type":"MacBook Pro","devices":["Mac15,7","Mac15,9","Mac15,11"],"hide_children":false,"subgroups":[]},{"name":"MacBook Pro (14-inch, Nov 2024)","key":"MacBook Pro (14-inch, Nov 2024)","type":"MacBook Pro","devices":["Mac16,1","Mac16,6","Mac16,8"],"hide_children":false,"subgroups":[]},{"name":"MacBook Pro (Retina, 15-inch, Late 2013)","key":"MacBook Pro (Retina, 15-inch, Late 2013)","type":"MacBook Pro","devices":["MacBookPro11,2-Late-2013","MacBookPro11,3-Late-2013"],"hide_children":false,"subgroups":[]},{"name":"MacBook Pro (14-inch, 2021)","key":"MacBook Pro (14-inch, 2021)","type":"MacBook Pro","devices":["MacBookPro18,3","MacBookPro18,4"],"hide_children":false,"subgroups":[]},{"name":"MacBook Pro (15-inch, 2019)","key":"MacBook Pro (15-inch, 2019)","type":"MacBook Pro","devices":["MacBookPro15,1-2019","MacBookPro15,3-2019"],"hide_children":false,"subgroups":[]},{"name":"MacBook Pro (16-inch, 2021)","key":"MacBook Pro (16-inch, 2021)","type":"MacBook Pro","devices":["MacBookPro18,1","MacBookPro18,2"],"hide_children":false,"subgroups":[]},{"name":"MacBook Pro (Retina, 15-inch, Mid 2014)","key":"MacBook Pro (Retina, 15-inch, Mid 2014)","type":"MacBook Pro","devices":["MacBookPro11,2-Mid-2014","MacBookPro11,3-Mid-2014"],"hide_children":false,"subgroups":[]},{"name":"MacBook Pro (13-inch, 2019)","key":"MacBook Pro (13-inch, 2019)","type":"MacBook Pro","devices":["MacBookPro15,2-2019","MacBookPro15,4"],"hide_children":false,"subgroups":[]},{"name":"MacBook Pro (15-inch, 2018)","key":"MacBook Pro (15-inch, 2018)","type":"MacBook Pro","devices":["MacBookPro15,1-2018","MacBookPro15,3-2018"],"hide_children":false,"subgroups":[]},{"name":"iTunes","key":"iTunes","type":"Software","devices":["iTunes (Windows, x64)","iTunes (Windows, x64, Older video cards)","iTunes (Windows, x86)","iTunes (macOS)"],"hide_children":false,"subgroups":[]},{"name":"Safari","key":"Safari","type":"Software","devices":["Safari (macOS)","Safari (Windows)"],"hide_children":false,"subgroups":[]},{"name":"Mac Pro (2023)","key":"Mac Pro (2023)","type":"Mac Pro","devices":["Mac14,8","Mac14,8-Rack"],"hide_children":false,"subgroups":[]},{"name":"Mac Pro (2019)","key":"Mac Pro (2019)","type":"Mac Pro","devices":["MacPro7,1","MacPro7,1-Rack"],"hide_children":false,"subgroups":[]},{"name":"Macintosh 512Ke","key":"Macintosh 512Ke","type":"Macintosh","devices":["Macintosh 512Ke","Macintosh ED"],"hide_children":false,"subgroups":[]},{"name":"Macintosh Plus","key":"Macintosh Plus","type":"Macintosh","devices":["Macintosh Plus","Macintosh Plus ED"],"hide_children":false,"subgroups":[]},{"name":"iPod shuffle","key":"iPod shuffle","type":"iPod shuffle","devices":["iPod shuffle (512 MB)","iPod shuffle (1 GB)","iPod Shuffle from HP Music Player (512 MB)","iPod Shuffle from HP Music Player (1 GB)"],"hide_children":false,"subgroups":[]},{"name":"iPod shuffle (4th generation)","key":"iPod shuffle (4th generation)","type":"iPod shuffle","devices":["iPod shuffle (4th generation)","iPod shuffle (4th generation Late 2012)","iPod shuffle (4th generation Mid 2015)"],"hide_children":false,"subgroups":[]},{"name":"iPod shuffle (3rd generation)","key":"iPod shuffle (3rd generation)","type":"iPod shuffle","devices":["iPod shuffle (3rd generation)","iPod shuffle (3rd generation Late 2009)"],"hide_children":false,"subgroups":[]},{"name":"iPod shuffle (2nd generation)","key":"iPod shuffle (2nd generation)","type":"iPod shuffle","devices":["iPod shuffle (2nd generation)","iPod shuffle (2nd generation)-avon"],"hide_children":false,"subgroups":[]},{"name":"Beats Pill (3rd generation)","key":"Beats Pill (3rd generation)","type":"Beats Speakers","devices":["BeatsPill1,2","BeatsPill1,2-kim"],"hide_children":false,"subgroups":[]},{"name":"Beats Pill+","key":"Beats Pill+","type":"Beats Speakers","devices":["Device1,9728","Device1,9728-stussy","Device1,9728-kar","Device1,9728-malbons","Device1,9728-quai","Device1,9728-kith","Device1,9728-undefeated","Device1,9728-faze","Device1,9728-madhappy","Device1,9728-recordings","Device1,9728-booker"],"hide_children":false,"subgroups":[]},{"name":"Beats Pill (1st generation)","key":"Beats Pill (1st generation)","type":"Beats Speakers","devices":["Beats Pill (1st generation)","Pretty Sweet Pill","Beats Pill (1st generation) Alexander Wang Edition","Beats Pill (1st generation) Barry McGee Edition","Beats Pill SE"],"hide_children":false,"subgroups":[]},{"name":"Beats Pill (2nd generation)","key":"Beats Pill (2nd generation)","type":"Beats Speakers","devices":["Beats Pill (2nd generation)","Beats Pill (2nd generation) Gloss Gold Edition","Beats Pill (2nd generation) MCM Edition","Beats Pill (2nd generation) Barry McGee Edition","Beats Pill (2nd generation) Nicki Minaj Edition","Beats Pill (2nd generation) fragment design Edition","Beats Pill (2nd generation) KITH Edition","Beats Pill (2nd generation) ColorWare Safari Edition","Beats Pill (2nd generation) Shady Records Edition"],"hide_children":false,"subgroups":[]},{"name":"Beats Wireless 1.5","key":"Beats Wireless 1.5","type":"Beats Headphones","devices":["Beats Wireless 1.5"],"hide_children":false,"subgroups":[]},{"name":"Beats Wireless","key":"Beats Wireless","type":"Beats Headphones","devices":["Beats Wireless"],"hide_children":false,"subgroups":[]},{"name":"Beats Solo²","key":"Beats Solo2","type":"Beats Headphones","devices":["Beats Solo2","Beats Solo2 Hello Kitty Edition","Beats Solo2 fragment design Edition","Beats Solo2 Chen Man - Year Of The Sheep Edition"],"hide_children":false,"subgroups":[]},{"name":"Beats Studio Pro","key":"Beats Studio Pro","type":"Beats Headphones","devices":["BeatsStudioPro1,1","BeatsStudioPro1,1-atlanta","BeatsStudioPro1,1-columbus","BeatsStudioPro1,1-miami","BeatsStudioPro1,1-la","BeatsStudioPro1,1-nashville","BeatsStudioPro1,1-nyc","BeatsStudioPro1,1-stl","BeatsStudioPro1,1-stussy","BeatsStudioPro1,1-toronto","BeatsStudioPro1,1-fragment","BeatsStudioPro1,1-windowsen","BeatsStudioPro1,1-kim"],"hide_children":false,"subgroups":[]},{"name":"Beats Studio (2nd generation)","key":"Beats Studio (2nd generation)","type":"Beats Headphones","devices":["Beats Studio (2nd generation)","Beats Studio (2nd generation) Chief Keef Edition"],"hide_children":false,"subgroups":[]},{"name":"Beats Solo³ Wireless","key":"Beats Solo3 Wireless","type":"Beats Headphones","devices":["BeatsSolo3,1","BeatsSolo3,1-mickey","BeatsSolo3,1-thirdman","BeatsSolo3,1-line","BeatsSolo3,1-newyears","BeatsSolo3,1-nayva","BeatsSolo3,1-mawalola"],"hide_children":false,"subgroups":[]},{"name":"Beats Pro","key":"Beats Pro","type":"Beats Headphones","devices":["Beats Pro","Beats Detox Pro","Beats Pro Illest Edition","Beats Pro Lamborghini Edition","Beats Pro Lil Wayne Edition","Beats Pro Fendi Edition","Beats Pro Nicki Minaj Edition","Beats Pro LeBron James MVP Edition"],"hide_children":false,"subgroups":[]},{"name":"Beats Studio (1st generation)","key":"Beats Studio (1st generation)","type":"Beats Headphones","devices":["Beats Studio (1st generation)","Beats Studio (1st generation) Illest Edition","Beats Studio (1st generation) Selfridges Edition","Beats Studio (1st generation) Nate Robinson Edition","Beats Studio (1st generation) Harley Davidson Edition","Beats Studio (1st generation) Staple Design Edition","Beats Studio (1st generation) Maserati Edition","Beats Studio (1st generation) Pigalle Edition","Beats Studio (1st generation) Milkcrate Athletics Edition","Beats Studio (1st generation) Red Sox Edition"],"hide_children":false,"subgroups":[]},{"name":"Beats Solo HD","key":"Beats Solo HD","type":"Beats Headphones","devices":["Beats Solo HD","Beats Solo HD BAPE Edition","Beats Solo HD Paris Saint-Germain Edition","Beats Solo HD Futura Edition","JustBeats Solo"],"hide_children":false,"subgroups":[]},{"name":"Beats Solo 4","key":"Beats Solo 4","type":"Beats Headphones","devices":["BeatsSolo4,1","BeatsSolo4,1-minecraft"],"hide_children":false,"subgroups":[]},{"name":"Beats Executive","key":"Beats Executive","type":"Beats Headphones","devices":["Beats Executive","Beats Executive colette Edition"],"hide_children":false,"subgroups":[]},{"name":"Beats Studio³ Wireless","key":"Beats Studio3 Wireless","type":"Beats Headphones","devices":["BeatsStudio3,2","BeatsStudio3,2-acw","BeatsStudio3,2-psychworld","BeatsStudio3,2-faze","BeatsStudio3,2-nba","BeatsStudio3,2-ghetto","BeatsStudio3,2-djkhaled","BeatsStudio3,2-cosmophone","BeatsStudio3,2-neymar","BeatsStudio3,2-violet","BeatsStudio3,2-connor","BeatsStudio3,2-madhappy","BeatsStudio3,2-highground"],"hide_children":false,"subgroups":[]},{"name":"Beats Solo","key":"Beats Solo","type":"Beats Headphones","devices":["Beats Solo"],"hide_children":false,"subgroups":[]},{"name":"Beats Studio Wireless","key":"Beats Studio Wireless","type":"Beats Headphones","devices":["Beats Studio Wireless","Beats Studio Wireless Alexander Wang Edition","Beats Studio Wireless Balmain Edition","Beats Studio Wireless Ellen Edition","Beats Studio Wireless Gloss Gold Edition","Beats Studio Wireless KITH Edition","Beats Studio Wireless MCM Edition","Beats Studio Wireless Pigalle Edition","Beats Studio Wireless Snarkitecture Edition","Beats Studio Wireless UNKNWN Edition","Beats Studio Wireless Unity Edition"],"hide_children":false,"subgroups":[]},{"name":"Beats Solo² Wireless","key":"Beats Solo2 Wireless","type":"Beats Headphones","devices":["Beats Solo2 Wireless","Beats Solo2 Wireless Year of the Monkey Edition","Beats Solo2 Wireless MLB All-Star Edition"],"hide_children":false,"subgroups":[]},{"name":"Beats Solo Pro","key":"Beats Solo Pro","type":"Beats Headphones","devices":["BeatsSoloPro1,1-eastside","BeatsSoloPro1,1-verdy","BeatsSoloPro1,1"],"hide_children":false,"subgroups":[]},{"name":"Beats Studio Buds","key":"Beats Studio Buds series","type":"Beats Earbuds","devices":["BeatsStudioBuds1,1-left","BeatsStudioBuds1,1-right","BeatsStudioBuds1,1-case","BeatsStudioBuds1,1-tiger-left","BeatsStudioBuds1,1-tiger-right","BeatsStudioBuds1,1-tiger-case","BeatsStudioBuds1,1-union-left","BeatsStudioBuds1,1-union-right","BeatsStudioBuds1,1-union-case","BeatsStudioBuds1,1-paper-left","BeatsStudioBuds1,1-paper-right","BeatsStudioBuds1,1-paper-case","BeatsStudioBuds1,1-nickmercs-left","BeatsStudioBuds1,1-nickmercs-right","BeatsStudioBuds1,1-nickmercs-case","BeatsStudioBuds1,1-futura-left","BeatsStudioBuds1,1-futura-right","BeatsStudioBuds1,1-futura-case"],"hide_children":false,"subgroups":[{"name":"Beats Studio Buds","key":"Beats Studio Buds","type":"Beats Earbuds","devices":["BeatsStudioBuds1,1-left","BeatsStudioBuds1,1-right","BeatsStudioBuds1,1-case"],"hide_children":false,"subgroups":[]},{"name":"Beats Studio Buds Year of the Tiger Edition","key":"Beats Studio Buds Year of the Tiger Edition","type":"Beats Earbuds","devices":["BeatsStudioBuds1,1-tiger-left","BeatsStudioBuds1,1-tiger-right","BeatsStudioBuds1,1-tiger-case"],"hide_children":false,"subgroups":[]},{"name":"Beats Studio Buds Union Edition","key":"Beats Studio Buds Union Edition","type":"Beats Earbuds","devices":["BeatsStudioBuds1,1-union-left","BeatsStudioBuds1,1-union-right","BeatsStudioBuds1,1-union-case"],"hide_children":false,"subgroups":[]},{"name":"Beats Studio Buds Daily Paper Edition","key":"Beats Studio Buds Daily Paper Edition","type":"Beats Earbuds","devices":["BeatsStudioBuds1,1-paper-left","BeatsStudioBuds1,1-paper-right","BeatsStudioBuds1,1-paper-case"],"hide_children":false,"subgroups":[]},{"name":"Beats Studio Buds NICKMERCS Edition","key":"Beats Studio Buds NICKMERCS Edition","type":"Beats Earbuds","devices":["BeatsStudioBuds1,1-nickmercs-left","BeatsStudioBuds1,1-nickmercs-right","BeatsStudioBuds1,1-nickmercs-case"],"hide_children":false,"subgroups":[]},{"name":"Beats Studio Buds FUTURA Edition","key":"Beats Studio Buds FUTURA Edition","type":"Beats Earbuds","devices":["BeatsStudioBuds1,1-futura-left","BeatsStudioBuds1,1-futura-right","BeatsStudioBuds1,1-futura-case"],"hide_children":false,"subgroups":[]}]},{"name":"Beats Solo Buds","key":"Beats Solo Buds series","type":"Beats Earbuds","devices":["BeatsSoloBuds1,1-left","BeatsSoloBuds1,1-right","BeatsSoloBuds1,1-case","BeatsSoloBuds1,1-festive-left","BeatsSoloBuds1,1-festive-right","BeatsSoloBuds1,1-festive-case"],"hide_children":false,"subgroups":[{"name":"Beats Solo Buds","key":"Beats Solo Buds","type":"Beats Earbuds","devices":["BeatsSoloBuds1,1-left","BeatsSoloBuds1,1-right","BeatsSoloBuds1,1-case"],"hide_children":false,"subgroups":[]},{"name":"Beats Solo Buds - Festive Special Edition","key":"Beats Solo Buds - Festive Special Edition","type":"Beats Earbuds","devices":["BeatsSoloBuds1,1-festive-left","BeatsSoloBuds1,1-festive-right","BeatsSoloBuds1,1-festive-case"],"hide_children":false,"subgroups":[]}]},{"name":"Powerbeats Pro (2020)","key":"Powerbeats Pro (2020) series","type":"Beats Earbuds","devices":["PowerbeatsPro2,1-left","PowerbeatsPro2,1-right","PowerbeatsPro2,1-case","PowerbeatsPro2,1-nba-left","PowerbeatsPro2,1-nba-right","PowerbeatsPro2,1-nba-case","PowerbeatsPro2,1-paria-left","PowerbeatsPro2,1-paria-right","PowerbeatsPro2,1-paria-case","PowerbeatsPro2,1-faze-left","PowerbeatsPro2,1-faze-right","PowerbeatsPro2,1-faze-case","PowerbeatsPro2,1-fragment-left","PowerbeatsPro2,1-fragment-right","PowerbeatsPro2,1-fragment-case","PowerbeatsPro2,1-samuel-left","PowerbeatsPro2,1-samuel-right","PowerbeatsPro2,1-samuel-case","PowerbeatsPro2,1-melody-left","PowerbeatsPro2,1-melody-right","PowerbeatsPro2,1-melody-case"],"hide_children":false,"subgroups":[{"name":"Powerbeats Pro (2020)","key":"Powerbeats Pro (2020)","type":"Beats Earbuds","devices":["PowerbeatsPro2,1-left","PowerbeatsPro2,1-right","PowerbeatsPro2,1-case"],"hide_children":false,"subgroups":[]},{"name":"Powerbeats Pro NBA x Better Edition","key":"Powerbeats Pro NBA x Better Edition","type":"Beats Earbuds","devices":["PowerbeatsPro2,1-nba-left","PowerbeatsPro2,1-nba-right","PowerbeatsPro2,1-nba-case"],"hide_children":false,"subgroups":[]},{"name":"Powerbeats Pro Yellow Paria Farzaneh Edition","key":"Powerbeats Pro Yellow Paria Farzaneh Edition","type":"Beats Earbuds","devices":["PowerbeatsPro2,1-paria-left","PowerbeatsPro2,1-paria-right","PowerbeatsPro2,1-paria-case"],"hide_children":false,"subgroups":[]},{"name":"Powerbeats Pro FaZe Clan Edition","key":"Powerbeats Pro FaZe Clan Edition","type":"Beats Earbuds","devices":["PowerbeatsPro2,1-faze-left","PowerbeatsPro2,1-faze-right","PowerbeatsPro2,1-faze-case"],"hide_children":false,"subgroups":[]},{"name":"Powerbeats Pro fragment design Edition","key":"Powerbeats Pro fragment design Edition","type":"Beats Earbuds","devices":["PowerbeatsPro2,1-fragment-left","PowerbeatsPro2,1-fragment-right","PowerbeatsPro2,1-fragment-case"],"hide_children":false,"subgroups":[]},{"name":"Powerbeats Pro Samuel Ross SR_A Edition","key":"Powerbeats Pro Samuel Ross SR_A Edition","type":"Beats Earbuds","devices":["PowerbeatsPro2,1-samuel-left","PowerbeatsPro2,1-samuel-right","PowerbeatsPro2,1-samuel-case"],"hide_children":false,"subgroups":[]},{"name":"Powerbeats Pro Melody Ehsani Edition","key":"Powerbeats Pro Melody Ehsani Edition","type":"Beats Earbuds","devices":["PowerbeatsPro2,1-melody-left","PowerbeatsPro2,1-melody-right","PowerbeatsPro2,1-melody-case"],"hide_children":false,"subgroups":[]}]},{"name":"Beats Flex","key":"Beats Flex","type":"Beats Earbuds","devices":["BeatsX2,1","BeatsX2,1-fragment","BeatsX2,1-wacko","BeatsX2,1-girlsdontcry"],"hide_children":false,"subgroups":[]},{"name":"Powerbeats (4th generation)","key":"Powerbeats (4th generation)","type":"Beats Earbuds","devices":["PowerBeats4,1","PowerBeats4,1-ambush"],"hide_children":false,"subgroups":[]},{"name":"Beats Fit Pro","key":"Beats Fit Pro series","type":"Beats Earbuds","devices":["BeatsFitPro1,1-left","BeatsFitPro1,1-right","BeatsFitPro1,1-case","BeatsFitPro1,1-alo-left","BeatsFitPro1,1-alo-right","BeatsFitPro1,1-alo-case","BeatsFitPro1,1-kim-left","BeatsFitPro1,1-kim-right","BeatsFitPro1,1-kim-case","BeatsFitPro1,1-fragment-left","BeatsFitPro1,1-fragment-right","BeatsFitPro1,1-fragment-case"],"hide_children":false,"subgroups":[{"name":"Beats Fit Pro","key":"Beats Fit Pro","type":"Beats Earbuds","devices":["BeatsFitPro1,1-left","BeatsFitPro1,1-right","BeatsFitPro1,1-case"],"hide_children":false,"subgroups":[]},{"name":"Beats Fit Pro Alo Edition","key":"Beats Fit Pro Alo Edition","type":"Beats Earbuds","devices":["BeatsFitPro1,1-alo-left","BeatsFitPro1,1-alo-right","BeatsFitPro1,1-alo-case"],"hide_children":false,"subgroups":[]},{"name":"Beats Fit Pro Kim K Edition","key":"Beats Fit Pro Kim K Edition","type":"Beats Earbuds","devices":["BeatsFitPro1,1-kim-right","BeatsFitPro1,1-kim-left","BeatsFitPro1,1-kim-case"],"hide_children":false,"subgroups":[]},{"name":"Beats Fit Pro fragment design Edition","key":"Beats Fit Pro fragment design Edition","type":"Beats Earbuds","devices":["BeatsFitPro1,1-fragment-right","BeatsFitPro1,1-fragment-left","BeatsFitPro1,1-fragment-case"],"hide_children":false,"subgroups":[]}]},{"name":"urBeats (1st generation)","key":"urBeats (1st generation)","type":"Beats Earbuds","devices":["urBeats (1st generation)","urBeats SE","urBeats (1st generation) Hello Kitty Edition","urBeats (1st generation) Alexander Wang Edition","urBeats (1st generation) Paris Saint-Germain Edition","urBeats (1st generation) Nicki Minaj Edition"],"hide_children":false,"subgroups":[]},{"name":"Powerbeats² Wireless","key":"Powerbeats2 Wireless","type":"Beats Earbuds","devices":["Powerbeats2 Wireless","Powerbeats2 Wireless UNDERCOVER Edition","Powerbeats2 Wireless KITH Edition"],"hide_children":false,"subgroups":[]},{"name":"Beats Studio Buds +","key":"Beats Studio Buds + series","type":"Beats Earbuds","devices":["BeatsStudioBuds1,2-left","BeatsStudioBuds1,2-right","BeatsStudioBuds1,2-case","BeatsStudioBuds1,2-olive-left","BeatsStudioBuds1,2-olive-right","BeatsStudioBuds1,2-olive-case"],"hide_children":false,"subgroups":[{"name":"Beats Studio Buds +","key":"Beats Studio Buds +","type":"Beats Earbuds","devices":["BeatsStudioBuds1,2-left","BeatsStudioBuds1,2-right","BeatsStudioBuds1,2-case"],"hide_children":false,"subgroups":[]},{"name":"Beats Studio Buds + Olive & June Edition","key":"Beats Studio Buds + Olive & June Edition","type":"Beats Earbuds","devices":["BeatsStudioBuds1,2-olive-left","BeatsStudioBuds1,2-olive-right","BeatsStudioBuds1,2-olive-case"],"hide_children":false,"subgroups":[]}]},{"name":"Powerbeats Pro (2019)","key":"Powerbeats Pro (2019)","type":"Beats Earbuds","devices":["PowerbeatsPro1,1-left","PowerbeatsPro1,1-right","PowerbeatsPro1,1-case"],"hide_children":false,"subgroups":[]},{"name":"urBeats³","key":"urBeats3","type":"Beats Earbuds","devices":["urBeats3-lightning","urBeats3"],"hide_children":false,"subgroups":[]},{"name":"Powerbeats Pro (2nd generation)","key":"Powerbeats Pro (2nd generation)","type":"Beats Earbuds","devices":["Device1,8221-left","Device1,8221-right","Device1,8221-case"],"hide_children":false,"subgroups":[]},{"name":"Powerbeats³ Wireless","key":"Powerbeats3 Wireless","type":"Beats Earbuds","devices":["PowerBeats3,1","PowerBeats3,1-balmain"],"hide_children":false,"subgroups":[]},{"name":"Beatsˣ","key":"BeatsX","type":"Beats Earbuds","devices":["BeatsX1,1","BeatsX1,1-sacai","BeatsX1,1-undefeated"],"hide_children":false,"subgroups":[]},{"name":"Powerbeats (1st generation)","key":"Powerbeats (1st generation)","type":"Beats Earbuds","devices":["Powerbeats (1st generation)","Powerbeats (1st generation) Lebron James Edition"],"hide_children":false,"subgroups":[]},{"name":"Beats Tour²","key":"Beats Tour2","type":"Beats Earbuds","devices":["Beats Tour2","Beats Tour2 MCM Edition","Beats Tour 2.5"],"hide_children":false,"subgroups":[]},{"name":"iBeats","key":"iBeats","type":"Beats Earbuds","devices":["iBeats","iBeats Justbeats"],"hide_children":false,"subgroups":[]},{"name":"Apple Watch Series 2","key":"Apple Watch Series 2","type":"Apple Watch","devices":["Watch2,3","Watch2,4"],"hide_children":false,"subgroups":[]},{"name":"Apple Watch Series 3","key":"Apple Watch Series 3","type":"Apple Watch","devices":["Watch3,1","Watch3,2","Watch3,3","Watch3,4"],"hide_children":false,"subgroups":[]},{"name":"Apple Watch Series 7","key":"Apple Watch Series 7","type":"Apple Watch","devices":["Watch6,6","Watch6,7","Watch6,8","Watch6,9"],"hide_children":false,"subgroups":[]},{"name":"Apple Watch Series 6","key":"Apple Watch Series 6","type":"Apple Watch","devices":["Watch6,1","Watch6,2","Watch6,3","Watch6,4"],"hide_children":false,"subgroups":[]},{"name":"Apple Watch SE (1st generation)","key":"Apple Watch SE (1st generation)","type":"Apple Watch","devices":["Watch5,9","Watch5,10","Watch5,11","Watch5,12"],"hide_children":false,"subgroups":[]},{"name":"Apple Watch (1st generation)","key":"Apple Watch (1st generation)","type":"Apple Watch","devices":["Watch1,1","Watch1,2"],"hide_children":false,"subgroups":[]},{"name":"Apple Watch SE (2nd generation)","key":"Apple Watch SE (2nd generation)","type":"Apple Watch","devices":["Watch6,10","Watch6,11","Watch6,12","Watch6,13"],"hide_children":false,"subgroups":[]},{"name":"Apple Watch Series 9","key":"Apple Watch Series 9","type":"Apple Watch","devices":["Watch7,1","Watch7,2","Watch7,3","Watch7,4"],"hide_children":false,"subgroups":[]},{"name":"Apple Watch Series 1","key":"Apple Watch Series 1","type":"Apple Watch","devices":["Watch2,6","Watch2,7"],"hide_children":false,"subgroups":[]},{"name":"Apple Watch Series 4","key":"Apple Watch Series 4","type":"Apple Watch","devices":["Watch4,1","Watch4,2","Watch4,3","Watch4,4"],"hide_children":false,"subgroups":[]},{"name":"Apple Watch Series 8","key":"Apple Watch Series 8","type":"Apple Watch","devices":["Watch6,14","Watch6,15","Watch6,16","Watch6,17"],"hide_children":false,"subgroups":[]},{"name":"Apple Watch Series 5","key":"Apple Watch Series 5","type":"Apple Watch","devices":["Watch5,1","Watch5,2","Watch5,3","Watch5,4"],"hide_children":false,"subgroups":[]},{"name":"Apple TV 4K (3rd generation)","key":"Apple TV 4K (3rd generation)","type":"Apple TV","devices":["AppleTV14,1","AppleTV14,1-wifi"],"hide_children":false,"subgroups":[]},{"name":"Apple TV (3rd generation)","key":"Apple TV (3rd generation)","type":"Apple TV","devices":["AppleTV3,1","AppleTV3,2"],"hide_children":false,"subgroups":[]},{"name":"iMac (24-inch, M1, 2021)","key":"iMac (24-inch, M1, 2021)","type":"iMac","devices":["iMac21,1","iMac21,2"],"hide_children":false,"subgroups":[]},{"name":"iMac (17-inch, Late 2006)","key":"iMac (17-inch, Late 2006)","type":"iMac","devices":["iMac5,1-17-inch","iMac5,2"],"hide_children":false,"subgroups":[]},{"name":"iMac Pro (Retina 5K, 27-inch, Late 2017)","key":"iMac Pro (Retina 5K, 27-inch, Late 2017)","type":"iMac","devices":["iMacPro1,1"],"hide_children":false,"subgroups":[]},{"name":"iMac (24-inch, M4, 2024)","key":"iMac (24-inch, M4, 2024)","type":"iMac","devices":["Mac16,2","Mac16,3"],"hide_children":false,"subgroups":[]},{"name":"iMac (24-inch, M3, 2023)","key":"iMac (24-inch, M3, 2023)","type":"iMac","devices":["Mac15,4","Mac15,5"],"hide_children":false,"subgroups":[]},{"name":"iMac (Retina 5K, 27-inch, 2020)","key":"iMac (Retina 5K, 27-inch, 2020)","type":"iMac","devices":["iMac20,1","iMac20,2"],"hide_children":false,"subgroups":[]},{"name":"HomePod mini","key":"HomePod mini","type":"HomePod","devices":["AudioAccessory5,1","AudioAccessory5,1-CHN"],"hide_children":false,"subgroups":[]},{"name":"HomePod (2nd generation)","key":"HomePod (2nd generation)","type":"HomePod","devices":["AudioAccessory6,1","AudioAccessory6,1-CHN"],"hide_children":false,"subgroups":[]},{"name":"HomePod (1st generation)","key":"HomePod (1st generation)","type":"HomePod","devices":["AudioAccessory1,1","AudioAccessory1,2"],"hide_children":false,"subgroups":[]}]

