{"os_str":"Xcode","version":"13.2","build":"13C90","key":"Xcode;13C90","released":"2021-12-13","rc":false,"beta":false,"rsr":false,"internal":false,"preinstalled":[],"appledb_web":{"web_image":{"id":"","align":"left"},"web_url":"https://appledb.dev/firmware/Xcode/13C90.html","api_url":"https://api.emiyl.com/firmware/Xcode/13C90.json","hide_from_latest_versions":false},"device_map":[{"name":"Xcode","key":"Xcode","released":["2003-09-28"]}],"device_group_map":[{"name":"Xcode","key":"Xcode","type":"","devices":["Xcode"],"hide_children":false,"subgroups":[]}],"sources":[{"type":"xip","device_map":["Xcode"],"links":[{"url":"https://developer.apple.com/services-account/download?path=/Developer_Tools/Xcode_13.2/Xcode_13.2.xip","active":true}],"hashes":{"sha1":"1e6bffb5623a56d33982f101520cde0a093d9f85"},"size":10747777272}]}