{"osStr":"watchOS","version":"2.0 beta 2","safariVersion":[],"build":"13S5255d","key":"watchOS;13S5255d","embeddedOSBuild":"","bridgeOSBuild":"","buildTrain":"BondiVail","released":"2015-06-30","rc":false,"beta":true,"rsr":false,"internal":false,"preinstalled":[],"notes":"","releaseNotes":"","securityNotes":"","ipd":{},"appledb":{"webImage":{"id":"","align":"left"},"webUrl":"https://appledb.dev/firmware/watchOS/13S5255d.html","apiUrl":"https://api.emiyl.com/firmware/watchOS/13S5255d.json","hideFromLatestVersions":false},"deviceMap":["Watch1,1","Watch1,2"],"osMap":[],"sources":[]}