{"os_str":"macOS","version":"15.0","safari_version":[],"build":"24A8332","key":"macOS;24A8332","embeddedOS_build":"","bridgeOS_build":"","build_train":"GlowHW","released":"2024-11-08","rc":false,"beta":false,"rsr":false,"internal":false,"preinstalled":["Mac16,1","Mac16,2","Mac16,3","Mac16,10"],"notes":"","release_notes":"","security_notes":"","ipd":{},"appledb_web":{"web_image":{"id":"Sequoia","align":"left"},"web_url":"https://appledb.dev/firmware/macOS/24A8332.html","api_url":"https://api.emiyl.com/firmware/macOS/24A8332.json","hide_from_latest_versions":true},"device_map":["Mac16,1","Mac16,2","Mac16,3","Mac16,10"],"os_map":[],"sources":[]}