{"os_str":"bridgeOS","version":"4.1","build":"17P1593","key":"bridgeOS;17P1593","released":"2019-11-13","rc":false,"beta":false,"rsr":false,"internal":false,"preinstalled":["iBridge2,14"],"appledb_web":{"web_image":{"id":"","align":"left"},"web_url":"https://appledb.dev/firmware/bridgeOS/17P1593.html","api_url":"https://api.emiyl.com/firmware/bridgeOS/17P1593.json","hide_from_latest_versions":false},"device_map":[{"name":"T2 (MacBookPro16,1)","key":"iBridge2,14","released":["2019-11-13"]}],"device_group_map":[{"name":"T2 (MacBookPro16,1)","key":"iBridge2,14","type":"","devices":["iBridge2,14"],"hide_children":false,"subgroups":[]}],"sources":[]}